LICENSE.txt
README.md
yato/__init__.py
yato/cli.py
yato/mermaid.py
yato/parser.py
yato/python_context.py
yato/storage.py
yato/yato.py
yato_lib-0.0.17.dist-info/LICENSE.txt
yato_lib-0.0.17.dist-info/METADATA
yato_lib-0.0.17.dist-info/WHEEL
yato_lib-0.0.17.dist-info/entry_points.txt
yato_lib-0.0.17.dist-info/RECORD
