Metadata-Version: 2.1
Name: yato-lib
Version: 0.0.17
Summary: The smallest DuckDB SQL transformations orchestrator
License: MIT
Keywords: duckdb,sql,orchestrator,etl
Author: Christophe Blefari
Author-email: yato@blef.fr
Requires-Python: >=3.9,<4.0
Classifier: Development Status :: 4 - Beta
Classifier: Intended Audience :: Developers
Classifier: License :: OSI Approved :: MIT License
Classifier: Operating System :: OS Independent
Classifier: Programming Language :: Python
Classifier: Programming Language :: Python :: 3
Classifier: Programming Language :: Python :: 3.9
Classifier: Programming Language :: Python :: 3.10
Classifier: Programming Language :: Python :: 3.11
Classifier: Programming Language :: Python :: 3.12
Provides-Extra: pandas
Requires-Dist: boto3 (>=1.34.51,<2.0.0)
Requires-Dist: click (>=8.1.7,<9.0.0)
Requires-Dist: duckdb (>=1.0.0,<2.0.0)
Requires-Dist: pandas (>=2.2.0,<3.0.0) ; extra == "pandas"
Requires-Dist: rich (>=13.7.1,<14.0.0)
Requires-Dist: sqlglot (>=23.0.2)
